agera5tools/__init__.py
agera5tools/agera5tools.yaml
agera5tools/build.py
agera5tools/check.py
agera5tools/cmd.py
agera5tools/db_data_provider.py
agera5tools/dump_clip.py
agera5tools/dump_grid.py
agera5tools/extract_point.py
agera5tools/grid_elevation_landfraction.nc
agera5tools/help.html
agera5tools/help.md
agera5tools/init.py
agera5tools/mirror.py
agera5tools/server.py
agera5tools/util.py
agera5tools/wdp.py
agera5tools-3.0.5.dist-info/licenses/LICENSE
agera5tools-3.0.5.dist-info/METADATA
agera5tools-3.0.5.dist-info/WHEEL
agera5tools-3.0.5.dist-info/entry_points.txt
agera5tools-3.0.5.dist-info/top_level.txt
agera5tools-3.0.5.dist-info/RECORD
