Metadata-Version: 2.4
Name: agera5tools
Version: 3.0.5
Summary: AgERA5 is a tool for handling AgERA5 data from the Copernicus Climate Data Store.
Author-email: Allard de Wit <allard.dewit@wur.nl>
Maintainer-email: Allard de Wit <allard.dewit@wur.nl>
License: MIT License
Project-URL: Homepage, https://github.com/ajwdewit/agera5tools
Project-URL: documentation, https://agera5tools.readthedocs.io
Project-URL: repository, https://github.com/ajwdewit/agera5tools.git
Classifier: Programming Language :: Python :: 3
Classifier: License :: OSI Approved :: MIT License
Classifier: Operating System :: OS Independent
Requires-Python: >=3.7
License-File: LICENSE
Requires-Dist: pandas>=2.0
Requires-Dist: PyYAML>=6.0
Requires-Dist: SQLAlchemy>=2.0
Requires-Dist: PyYAML>=6.0
Requires-Dist: xarray>=2023.6.0
Requires-Dist: dask>=2023.0.0
Requires-Dist: click>=8.1
Requires-Dist: flask>=2.2
Requires-Dist: cdsapi>=0.7.5
Requires-Dist: dotmap>=1.3
Requires-Dist: netCDF4>=1.6
Requires-Dist: requests>=2.28
Requires-Dist: wsgiserver>=1.3
Requires-Dist: duckdb>=1.1.3
Requires-Dist: duckdb_engine>=0.13.6
Requires-Dist: tqdm
Dynamic: license-file
